README.md
setup.py
elc_flow.egg-info/PKG-INFO
elc_flow.egg-info/SOURCES.txt
elc_flow.egg-info/dependency_links.txt
elc_flow.egg-info/top_level.txt
elcflow/__init__.py
elcflow/base.py
elcflow/builtin_operators.py
elcflow/defs.py
elcflow/graph.py
elcflow/helpers.py
elcflow/utils.py