Metadata-Version: 2.1
Name: elc-flow
Version: 0.2.0
Summary: A graph flow engine for East Low Carbon
Home-page: https://github.com/eggachecat/elc-flow-engine
Author: sunao
Author-email: sunao_0626@hotmail.com
License: UNKNOWN
Platform: UNKNOWN
Classifier: Programming Language :: Python :: 3
